lightpredict/__init__.py
lightpredict-0.5.dist-info/LICENSE.txt
lightpredict-0.5.dist-info/METADATA
lightpredict-0.5.dist-info/WHEEL
lightpredict-0.5.dist-info/top_level.txt
lightpredict-0.5.dist-info/RECORD
