Metadata-Version: 2.1
Name: lightpredict
Version: 0.5
Summary: Test 1
Home-page: https://github.com/arnavrneo/LightPredict
Author: Arnav Raina
Author-email: arnavr.neo@gmail.com
License: UNKNOWN
Keywords: machine learning,scikit learn,sklearn,ai,optuna,hyperparameters
Platform: UNKNOWN
License-File: LICENSE.txt
Requires-Dist: numpy
Requires-Dist: pandas
Requires-Dist: matplotlib
Requires-Dist: sklearn
Requires-Dist: optuna
